aoc/__init__.py
aoc/cli.py
aoc/config.py
aoc/util.py
aoc-1.0.1.dist-info/LICENSE
aoc-1.0.1.dist-info/METADATA
aoc-1.0.1.dist-info/WHEEL
aoc-1.0.1.dist-info/entry_points.txt
aoc-1.0.1.dist-info/top_level.txt
aoc-1.0.1.dist-info/RECORD
