Metadata-Version: 2.1
Name: aoc
Version: 1.0.1
Summary: Multi-cluster management tool
Home-page: https://github.com/Avielyo10/aoc.git
Author: Aviel Yosef
Author-email: Avielyo10@gmail.com
License: UNKNOWN
Platform: UNKNOWN
Classifier: Programming Language :: Python :: 3
Classifier: License :: OSI Approved :: MIT License
Classifier: Operating System :: OS Independent
Requires-Python: >=3.5
License-File: LICENSE
Requires-Dist: Click (>=7.1.2)
Requires-Dist: PyYAML (>=5.4.1)
Requires-Dist: tabulate (>=0.8.9)
